helixtelemetry/__init__.py
helixtelemetry/py.typed
helixtelemetry/telemetry/__init__.py
helixtelemetry/telemetry/register.py
helixtelemetry/telemetry/context/__init__.py
helixtelemetry/telemetry/context/telemetry_context.py
helixtelemetry/telemetry/factory/__init__.py
helixtelemetry/telemetry/factory/telemetry_factory.py
helixtelemetry/telemetry/metrics/__init__.py
helixtelemetry/telemetry/metrics/telemetry_counter.py
helixtelemetry/telemetry/metrics/telemetry_histogram_counter.py
helixtelemetry/telemetry/metrics/telemetry_up_down_counter.py
helixtelemetry/telemetry/providers/__init__.py
helixtelemetry/telemetry/providers/console_telemetry.py
helixtelemetry/telemetry/providers/null_telemetry.py
helixtelemetry/telemetry/providers/open_telemetry.py
helixtelemetry/telemetry/providers/telemetry.py
helixtelemetry/telemetry/spans/__init__.py
helixtelemetry/telemetry/spans/console_telemetry_span_wrapper.py
helixtelemetry/telemetry/spans/null_telemetry_span_wrapper.py
helixtelemetry/telemetry/spans/open_telemetry_span.py
helixtelemetry/telemetry/spans/telemetry_span_creator.py
helixtelemetry/telemetry/spans/telemetry_span_wrapper.py
helixtelemetry/telemetry/structures/__init__.py
helixtelemetry/telemetry/structures/console_telemetry_history_item.py
helixtelemetry/telemetry/structures/telemetry_attribute_value.py
helixtelemetry/telemetry/structures/telemetry_parent.py
helixtelemetry/telemetry/structures/telemetry_tracers.py
helixtelemetry/telemetry/test/__init__.py
helixtelemetry/telemetry/test/test_open_telemetry.py
helixtelemetry/telemetry/test/test_open_telemetry_multi_thread.py
helixtelemetry/telemetry/test/test_open_telemetry_raw.py
helixtelemetry/telemetry/test/test_open_telemetry_raw_multi_thread.py
helixtelemetry/telemetry/utilities/__init__.py
helixtelemetry/telemetry/utilities/mapping_appender.py
helixtelemetry-1.0.10.dist-info/licenses/LICENSE
tests/__init__.py
helixtelemetry-1.0.10.dist-info/METADATA
helixtelemetry-1.0.10.dist-info/WHEEL
helixtelemetry-1.0.10.dist-info/top_level.txt
helixtelemetry-1.0.10.dist-info/RECORD
